tortoise_serializer/__init__.py
tortoise_serializer/exceptions.py
tortoise_serializer/mixins.py
tortoise_serializer/protocols.py
tortoise_serializer/resolver.py
tortoise_serializer/serializers.py
tortoise_serializer/types.py
tortoise_serializer/utils/__init__.py
tortoise_serializer/utils/fields.py
tortoise_serializer-1.7.2.dist-info/METADATA
tortoise_serializer-1.7.2.dist-info/WHEEL
tortoise_serializer-1.7.2.dist-info/licenses/LICENSE
tortoise_serializer-1.7.2.dist-info/RECORD
