Metadata-Version: 2.4
Name: tortoise-serializer
Version: 1.7.2
Summary: Pydantic serialization for tortoise-orm
License-Expression: MIT
License-File: LICENSE
Author: Sebastien Nicolet
Author-email: snicolet95@gmail.com
Requires-Python: >=3.12
Classifier: Programming Language :: Python :: 3
Classifier: Programming Language :: Python :: 3.12
Classifier: Programming Language :: Python :: 3.13
Classifier: Programming Language :: Python :: 3.14
Requires-Dist: frozendict (>=2.4.6)
Requires-Dist: pydantic (>=2.12.2,<3.0.0)
Requires-Dist: structlog (>=25.4.0,<26.0.0)
Requires-Dist: tortoise-orm (>=0.25.1)
